tests/__init__.py
tests/test_scraper.py
web_scraping_toolkit/__init__.py
web_scraping_toolkit/parser.py
web_scraping_toolkit/scraper.py
web_scraping_toolkit/utils.py
web_scraping_toolkit-0.1.0.dist-info/METADATA
web_scraping_toolkit-0.1.0.dist-info/WHEEL
web_scraping_toolkit-0.1.0.dist-info/entry_points.txt
web_scraping_toolkit-0.1.0.dist-info/top_level.txt
web_scraping_toolkit-0.1.0.dist-info/RECORD
