Metadata-Version: 2.1
Name: web_scraping_toolkit
Version: 0.1.0
Summary: A toolkit for web scraping
Home-page: https://github.com/21Vijeth/web_scraping_toolkit.git
Author: Vijeth21
Author-email: vijethfernandes21@gmail.com
Classifier: Programming Language :: Python :: 3
Classifier: License :: OSI Approved :: MIT License
Classifier: Operating System :: OS Independent
Requires-Python: >=3.6
Requires-Dist: requests
Requires-Dist: beautifulsoup4
